content_composer/__init__.py
content_composer/langgraph_workflow.py
content_composer/py.typed
content_composer/recipe_loader.py
content_composer/recipe_parser.py
content_composer/reference_resolver.py
content_composer/state.py
content_composer/registry/__init__.py
content_composer/registry/decorators.py
content_composer/registry/discovery.py
content_composer/registry/metadata.py
content_composer/registry/registry.py
content_composer-0.1.2.dist-info/METADATA
content_composer-0.1.2.dist-info/WHEEL
content_composer-0.1.2.dist-info/RECORD
