Metadata-Version: 2.4
Name: content-composer
Version: 0.1.2
Summary: Content Composer is a tool for creating extremely powerful content pipelines using AI.
Requires-Python: >=3.10.6
Requires-Dist: ai-prompter>=0.1.0
Requires-Dist: esperanto>=2.1.1
Requires-Dist: langgraph>=0.4.8
Requires-Dist: loguru>=0.7.3
Requires-Dist: python-dotenv>=1.1.0
Requires-Dist: pyyaml>=6.0.2
